Metadata-Version: 2.1
Name: curver
Version: 0.5.1
Summary: 'For calculations in the curve complex'
Home-page: https://github.com/MarkCBell/curver
Author: Mark Bell
Author-email: mcbell@illinois.edu
License: MIT
Keywords: mapping class group,mapping classes,laminations
Classifier: Development Status :: 3 - Alpha
Classifier: Intended Audience :: Education
Classifier: Intended Audience :: Science/Research
Classifier: License :: OSI Approved :: MIT License
Classifier: Natural Language :: English
Classifier: Operating System :: OS Independent
Classifier: Programming Language :: Python
Classifier: Topic :: Scientific/Engineering :: Mathematics
Requires-Python: >=3.6
License-File: LICENSE
Requires-Dist: decorator>=4.3.0
Requires-Dist: networkx>=2.0
Requires-Dist: numpy>=1.15.1
Requires-Dist: realalg>=0.3.1
